Workbook

Sheet Assumptions
A1: Azure Bay Residences (Synthetic) — 850-Unit Luxury Condo Demo Workbook
A3: Sheets included:
A4: • Units_Residents — unit roster, owners/tenants, parking/boat/storage assignments
A5: • Accounts_AR — monthly assessments, balances, delinquency bucketing (formula-based)
A6: • Work_Orders — recent and active maintenance tickets
A7: • Violations — recent and active compliance items
A8: • Notices — board/management communications
A9: • Amenities_Parking — parking inventory and assignments
A10: • Amenities_BoatSlips — marina slip inventory and assignments
A11: • Vendors — vendor directory
A12: • SMS_Test_Set — example owner/resident questions for SMS/voice demos
A15: Tip: Demo flows that land well: balance/last payment, parking/boat slip, open work orders, and violations.

Sheet README

Sheet Units_Residents
A1: Unit | B1: Floor | C1: Stack | D1: Unit Type | E1: SqFt | F1: Occupancy Type | G1: Owner Name | H1: Owner Phone | I1: Owner Email | J1: Tenant Name | K1: Lease Expiration | L1: Parking Primary | M1: Parking Secondary | N1: Boat Slip | O1: Storage Unit | P1: SMS Opt-In
A2: 101 | B2: 1 | C2: 1 | D2: 1BR | E2: 934 | F2: Owner | G2: Henry Delgado | H2: (305) 555-1001 | I2: henry.delgado+101@demo-hoa.example | L2: P5-120 | P2: Y
A3: 102 | B3: 1 | C3: 2 | D3: 1BR | E3: 966 | F3: Renter | G3: Evelyn Gutierrez | H3: (305) 555-1002 | I3: evelyn.gutierrez+102@demo-hoa.example | J3: Benjamin Perez | K3: 46234 | L3: P4-124 | O3: S-234 | P3: Y
A4: 103 | B4: 1 | C4: 3 | D4: 1BR | E4: 915 | F4: Renter | G4: Mason Hernandez | H4: (305) 555-1003 | I4: mason.hernandez+103@demo-hoa.example | J4: Madison Perez | K4: 46259 | L4: P3-007 | P4: Y
A5: 104 | B5: 1 | C5: 4 | D5: 1BR | E5: 876 | F5: Owner | G5: Charlotte Gutierrez | H5: (305) 555-1004 | I5: charlotte.gutierrez+104@demo-hoa.example | L5: P2-058 | O5: S-039 | P5: Y
A6: 105 | B6: 1 | C6: 5 | D6: 1BR | E6: 877 | F6: Renter | G6: Emily Rivera | H6: (305) 555-1005 | I6: emily.rivera+105@demo-hoa.example | J6: Henry Gonzalez | K6: 46186 | L6: P1-035 | O6: S-094 | P6: Y
A7: 106 | B7: 1 | C7: 6 | D7: 1BR | E7: 855 | F7: Owner | G7: Noah Rodriguez | H7: (305) 555-1006 | I7: noah.rodriguez+106@demo-hoa.example | L7: P1-033 | O7: S-046 | P7: Y
A8: 107 | B8: 1 | C8: 7 | D8: 2BR | E8: 1450 | F8: Renter | G8: Lucas Flores | H8: (305) 555-1007 | I8: lucas.flores+107@demo-hoa.example | J8: Mia Martinez | K8: 46228 | L8: P2-279 | N8: B-035 | P8: N
A9: 108 | B9: 1 | C9: 8 | D9: 2BR | E9: 1485 | F9: Owner | G9: Abigail Ramirez | H9: (305) 555-1008 | I9: abigail.ramirez+108@demo-hoa.example | L9: P3-148 | N9: B-027 | O9: S-175 | P9: Y
A10: 109 | B10: 1 | C10: 9 | D10: 2BR | E10: 1393 | F10: Owner | G10: Evelyn Gomez | H10: (305) 555-1009 | I10: evelyn.gomez+109@demo-hoa.example | L10: P1-126 | M10: P3-190 | P10: N
A11: 110 | B11: 1 | C11: 10 | D11: 2BR | E11: 1190 | F11: Owner | G11: Charlotte Gomez | H11: (305) 555-1010 | I11: charlotte.gomez+110@demo-hoa.example | L11: P4-172 | M11: P2-229 | O11: S-198 | P11: Y
A12: 111 | B12: 1 | C12: 11 | D12: 2BR | E12: 1233 | F12: Owner | G12: Logan Rivera | H12: (305) 555-1011 | I12: logan.rivera+111@demo-hoa.example | L12: P1-188 | O12: S-309 | P12: Y
A13: 112 | B13: 1 | C13: 12 | D13: 2BR | E13: 1503 | F13: Owner | G13: Madison Morales | H13: (305) 555-1012 | I13: madison.morales+112@demo-hoa.example | L13: P1-244 | M13: P5-088 | O13: S-187 | P13: N
A14: 113 | B14: 1 | C14: 13 | D14: 3BR | E14: 2177 | F14: Renter | G14: Logan Ortiz | H14: (305) 555-1013 | I14: logan.ortiz+113@demo-hoa.example | J14: Amelia Martinez | K14: 46505 | L14: P1-236 | M14: P2-091 | O14: S-137 | P14: N
A15: 114 | B15: 1 | C15: 14 | D15: 3BR | E15: 1777 | F15: Owner | G15: Charlotte Romero | H15: (305) 555-1014 | I15: charlotte.romero+114@demo-hoa.example | L15: P5-207 | M15: P3-279 | P15: Y
A16: 115 | B16: 1 | C16: 15 | D16: 3BR | E16: 2181 | F16: Renter | G16: Michael Reyes | H16: (305) 555-1015 | I16: michael.reyes+115@demo-hoa.example | J16: Noah Reyes | K16: 46400 | L16: P3-087 | M16: P4-018 | N16: B-030 | O16: S-001 | P16: Y
A17: 116 | B17: 1 | C17: 16 | D17: 3BR | E17: 2086 | F17: Renter | G17: James Morales | H17: (305) 555-1016 | I17: james.morales+116@demo-hoa.example | J17: Liam Romero | K17: 46294 | L17: P5-137 | O17: S-215 | P17: N
A18: 117 | B18: 1 | C18: 17 | D18: PH | E18: 3544 | F18: Owner | G18: Michael Alvarez | H18: (305) 555-1017 | I18: michael.alvarez+117@demo-hoa.example | L18: P2-234 | M18: P1-133 | P18: Y
A19: 201 | B19: 2 | C19: 1 | D19: 1BR | E19: 852 | F19: Owner | G19: Charlotte Ramos | H19: (305) 555-1018 | I19: charlotte.ramos+201@demo-hoa.example | L19: P4-120 | O19: S-009 | P19: Y
A20: 202 | B20: 2 | C20: 2 | D20: 1BR | E20: 914 | F20: Owner | G20: Evelyn Gomez | H20: (305) 555-1019 | I20: evelyn.gomez+202@demo-hoa.example | L20: P2-088 | O20: S-188 | P20: Y
A21: 203 | B21: 2 | C21: 3 | D21: 1BR | E21: 849 | F21: Owner | G21: Sebastian Chavez | H21: (305) 555-1020 | I21: sebastian.chavez+203@demo-hoa.example | L21: P5-210 | O21: S-270 | P21: Y
A22: 204 | B22: 2 | C22: 4 | D22: 1BR | E22: 874 | F22: Owner | G22: Sophia Navarro | H22: (305) 555-1021 | I22: sophia.navarro+204@demo-hoa.example | L22: P4-048 | O22: S-123 | P22: Y
A23: 205 | B23: 2 | C23: 5 | D23: 1BR | E23: 842 | F23: Owner | G23: Mason Vega | H23: (305) 555-1022 | I23: mason.vega+205@demo-hoa.example | L23: P3-024 | O23: S-216 | P23: Y
A24: 206 | B24: 2 | C24: 6 | D24: 1BR | E24: 864 | F24: Owner | G24: Isabella Delgado | H24: (305) 555-1023 | I24: isabella.delgado+206@demo-hoa.example | L24: P1-182 | O24: S-266 | P24: Y
A25: 207 | B25: 2 | C25: 7 | D25: 2BR | E25: 1473 | F25: Renter | G25: Logan Gonzalez | H25: (305) 555-1024 | I25: logan.gonzalez+207@demo-hoa.example | J25: Alexander Vega | K25: 46157 | L25: P1-012 | M25: P3-218 | P25: Y
A26: 208 | B26: 2 | C26: 8 | D26: 2BR | E26: 1474 | F26: Renter | G26: Emily Hernandez | H26: (305) 555-1025 | I26: emily.hernandez+208@demo-hoa.example | J26: Harper Morales | K26: 46441 | L26: P1-191 | M26: P5-198 | P26: Y
A27: 209 | B27: 2 | C27: 9 | D27: 2BR | E27: 1246 | F27: Renter | G27: Liam Ruiz | H27: (305) 555-1026 | I27: liam.ruiz+209@demo-hoa.example | J27: Mia Gutierrez | K27: 46194 | L27: P1-185 | M27: P2-245 | O27: S-150 | P27: Y
A28: 210 | B28: 2 | C28: 10 | D28: 2BR | E28: 1325 | F28: Owner | G28: Logan Torres | H28: (305) 555-1027 | I28: logan.torres+210@demo-hoa.example | L28: P1-010 | M28: P5-228 | O28: S-162 | P28: Y
A29: 211 | B29: 2 | C29: 11 | D29: 2BR | E29: 1483 | F29: Owner | G29: Michael Vega | H29: (305) 555-1028 | I29: michael.vega+211@demo-hoa.example | L29: P1-100 | P29: N
A30: 212 | B30: 2 | C30: 12 | D30: 2BR | E30: 1221 | F30: Renter | G30: Amelia Castillo | H30: (305) 555-1029 | I30: amelia.castillo+212@demo-hoa.example | J30: Isabella Suarez | K30: 46408 | L30: P4-043 | O30: S-253 | P30: Y
A31: 213 | B31: 2 | C31: 13 | D31: 3BR | E31: 1900 | F31: Owner | G31: Noah Mendoza | H31: (305) 555-1030 | I31: noah.mendoza+213@demo-hoa.example | L31: P4-060 | M31: P3-282 | P31: Y
A32: 214 | B32: 2 | C32: 14 | D32: 3BR | E32: 1970 | F32: Renter | G32: Jackson Gomez | H32: (305) 555-1031 | I32: jackson.gomez+214@demo-hoa.example | J32: Charlotte Gonzalez | K32: 46496 | L32: P2-015 | M32: P5-111 | O32: S-081 | P32: Y
A33: 215 | B33: 2 | C33: 15 | D33: 3BR | E33: 1794 | F33: Owner | G33: Charlotte Navarro | H33: (305) 555-1032 | I33: charlotte.navarro+215@demo-hoa.example | L33: P5-284 | O33: S-250 | P33: Y
A34: 216 | B34: 2 | C34: 16 | D34: 3BR | E34: 1970 | F34: Renter | G34: Elijah Gutierrez | H34: (305) 555-1033 | I34: elijah.gutierrez+216@demo-hoa.example | J34: Harper Ortiz | K34: 46260 | L34: P5-105 | M34: P2-005 | P34: N
A35: 217 | B35: 2 | C35: 17 | D35: PH | E35: 2899 | F35: Owner | G35: Elijah Vargas | H35: (305) 555-1034 | I35: elijah.vargas+217@demo-hoa.example | L35: P1-101 | M35: P1-022 | P35: N
A36: 301 | B36: 3 | C36: 1 | D36: 1BR | E36: 930 | F36: Renter | G36: James Martinez | H36: (305) 555-1035 | I36: james.martinez+301@demo-hoa.example | J36: Charlotte Martinez | K36: 46412 | L36: P5-135 | O36: S-017 | P36: Y
A37: 302 | B37: 3 | C37: 2 | D37: 1BR | E37: 949 | F37: Renter | G37: Mia Gonzalez | H37: (305) 555-1036 | I37: mia.gonzalez+302@demo-hoa.example | J37: Mia Diaz | K37: 46285 | L37: P4-081 | P37: Y
A38: 303 | B38: 3 | C38: 3 | D38: 1BR | E38: 974 | F38: Owner | G38: Liam Gonzalez | H38: (305) 555-1037 | I38: liam.gonzalez+303@demo-hoa.example | L38: P5-002 | P38: Y
A39: 304 | B39: 3 | C39: 4 | D39: 1BR | E39: 858 | F39: Owner | G39: Alexander Rivera | H39: (305) 555-1038 | I39: alexander.rivera+304@demo-hoa.example | L39: P3-284 | O39: S-142 | P39: Y
A40: 305 | B40: 3 | C40: 5 | D40: 1BR | E40: 896 | F40: Renter | G40: Logan Ortiz | H40: (305) 555-1039 | I40: logan.ortiz+305@demo-hoa.example | J40: Sofia Ramos | K40: 46260 | L40: P4-254 | P40: Y
A41: 306 | B41: 3 | C41: 6 | D41: 1BR | E41: 926 | F41: Owner | G41: Elijah Torres | H41: (305) 555-1040 | I41: elijah.torres+306@demo-hoa.example | L41: P3-140 | P41: Y
A42: 307 | B42: 3 | C42: 7 | D42: 2BR | E42: 1296 | F42: Owner | G42: Evelyn Castillo | H42: (305) 555-1041 | I42: evelyn.castillo+307@demo-hoa.example | L42: P1-127 | P42: N
A43: 308 | B43: 3 | C43: 8 | D43: 2BR | E43: 1196 | F43: Owner | G43: Olivia Reyes | H43: (305) 555-1042 | I43: olivia.reyes+308@demo-hoa.example | L43: P4-257 | M43: P5-110 | P43: Y
A44: 309 | B44: 3 | C44: 9 | D44: 2BR | E44: 1211 | F44: Owner | G44: Olivia Alvarez | H44: (305) 555-1043 | I44: olivia.alvarez+309@demo-hoa.example | L44: P5-021 | M44: P2-227 | O44: S-140 | P44: Y
A45: 310 | B45: 3 | C45: 10 | D45: 2BR | E45: 1355 | F45: Renter | G45: Michael Alvarez | H45: (305) 555-1044 | I45: michael.alvarez+310@demo-hoa.example | J45: Emily Delgado | K45: 46463 | L45: P2-252 | O45: S-231 | P45: Y
A46: 311 | B46: 3 | C46: 11 | D46: 2BR | E46: 1332 | F46: Renter | G46: Elijah Rivera | H46: (305) 555-1045 | I46: elijah.rivera+311@demo-hoa.example | J46: Elijah Gomez | K46: 46373 | L46: P4-262 | M46: P1-016 | P46: N
A47: 312 | B47: 3 | C47: 12 | D47: 2BR | E47: 1356 | F47: Owner | G47: Sofia Hernandez | H47: (305) 555-1046 | I47: sofia.hernandez+312@demo-hoa.example | L47: P2-085 | M47: P5-130 | P47: Y
A48: 313 | B48: 3 | C48: 13 | D48: 3BR | E48: 1927 | F48: Renter | G48: Sophia Lopez | H48: (305) 555-1047 | I48: sophia.lopez+313@demo-hoa.example | J48: Alexander Romero | K48: 46402 | L48: P2-176 | M48: P3-049 | P48: Y
A49: 314 | B49: 3 | C49: 14 | D49: 3BR | E49: 2073 | F49: Renter | G49: Mia Alvarez | H49: (305) 555-1048 | I49: mia.alvarez+314@demo-hoa.example | J49: Madison Gonzalez | K49: 46142 | L49: P4-112 | O49: S-261 | P49: N
A50: 315 | B50: 3 | C50: 15 | D50: 3BR | E50: 1854 | F50: Owner | G50: Emily Martinez | H50: (305) 555-1049 | I50: emily.martinez+315@demo-hoa.example | L50: P5-189 | O50: S-262 | P50: Y
A51: 316 | B51: 3 | C51: 16 | D51: 3BR | E51: 2077 | F51: Renter | G51: Liam Ruiz | H51: (305) 555-1050 | I51: liam.ruiz+316@demo-hoa.example | J51: Charlotte Delgado | K51: 46340 | L51: P3-181 | P51: N
A52: 317 | B52: 3 | C52: 17 | D52: PH | E52: 3486 | F52: Owner | G52: Emily Chavez | H52: (305) 555-1051 | I52: emily.chavez+317@demo-hoa.example | L52: P5-191 | M52: P5-142 | O52: S-061 | P52: Y
A53: 401 | B53: 4 | C53: 1 | D53: 1BR | E53: 848 | F53: Owner | G53: Sofia Perez | H53: (305) 555-1052 | I53: sofia.perez+401@demo-hoa.example | L53: P1-214 | O53: S-240 | P53: Y
A54: 402 | B54: 4 | C54: 2 | D54: 1BR | E54: 869 | F54: Owner | G54: Noah Diaz | H54: (305) 555-1053 | I54: noah.diaz+402@demo-hoa.example | L54: P2-248 | P54: Y
A55: 403 | B55: 4 | C55: 3 | D55: 1BR | E55: 902 | F55: Owner | G55: Harper Suarez | H55: (305) 555-1054 | I55: harper.suarez+403@demo-hoa.example | L55: P5-215 | O55: S-238 | P55: Y
A56: 404 | B56: 4 | C56: 4 | D56: 1BR | E56: 966 | F56: Owner | G56: Lucas Martinez | H56: (305) 555-1055 | I56: lucas.martinez+404@demo-hoa.example | L56: P2-230 | P56: Y
A57: 405 | B57: 4 | C57: 5 | D57: 1BR | E57: 948 | F57: Renter | G57: Mason Gomez | H57: (305) 555-1056 | I57: mason.gomez+405@demo-hoa.example | J57: Alexander Ramirez | K57: 46219 | L57: P2-136 | P57: N
A58: 406 | B58: 4 | C58: 6 | D58: 1BR | E58: 915 | F58: Renter | G58: Ella Sanchez | H58: (305) 555-1057 | I58: ella.sanchez+406@demo-hoa.example | J58: Madison Ramirez | K58: 46444 | L58: P4-072 | N58: B-029 | P58: Y
A59: 407 | B59: 4 | C59: 7 | D59: 2BR | E59: 1219 | F59: Renter | G59: Grace Gutierrez | H59: (305) 555-1058 | I59: grace.gutierrez+407@demo-hoa.example | J59: Isabella Ramos | K59: 46369 | L59: P1-173 | M59: P4-217 | P59: Y
A60: 408 | B60: 4 | C60: 8 | D60: 2BR | E60: 1430 | F60: Owner | G60: Liam Morales | H60: (305) 555-1059 | I60: liam.morales+408@demo-hoa.example | L60: P5-084 | M60: P4-250 | O60: S-211 | P60: Y
A61: 409 | B61: 4 | C61: 9 | D61: 2BR | E61: 1191 | F61: Renter | G61: Michael Sanchez | H61: (305) 555-1060 | I61: michael.sanchez+409@demo-hoa.example | J61: Abigail Hernandez | K61: 46138 | L61: P3-133 | M61: P1-108 | O61: S-105 | P61: N
A62: 410 | B62: 4 | C62: 10 | D62: 2BR | E62: 1421 | F62: Owner | G62: Madison Gonzalez | H62: (305) 555-1061 | I62: madison.gonzalez+410@demo-hoa.example | L62: P1-215 | P62: Y
A63: 411 | B63: 4 | C63: 11 | D63: 2BR | E63: 1409 | F63: Owner | G63: Daniel Navarro | H63: (305) 555-1062 | I63: daniel.navarro+411@demo-hoa.example | L63: P3-131 | M63: P5-081 | P63: Y
A64: 412 | B64: 4 | C64: 12 | D64: 2BR | E64: 1381 | F64: Renter | G64: Lucas Ruiz | H64: (305) 555-1063 | I64: lucas.ruiz+412@demo-hoa.example | J64: Ava Suarez | K64: 46134 | L64: P5-127 | M64: P2-112 | P64: Y
A65: 413 | B65: 4 | C65: 13 | D65: 3BR | E65: 2121 | F65: Owner | G65: Isabella Cruz | H65: (305) 555-1064 | I65: isabella.cruz+413@demo-hoa.example | L65: P3-278 | N65: B-023 | P65: Y
A66: 414 | B66: 4 | C66: 14 | D66: 3BR | E66: 1896 | F66: Owner | G66: Alexander Martinez | H66: (305) 555-1065 | I66: alexander.martinez+414@demo-hoa.example | L66: P4-194 | M66: P2-071 | P66: Y
A67: 415 | B67: 4 | C67: 15 | D67: 3BR | E67: 2099 | F67: Owner | G67: Madison Navarro | H67: (305) 555-1066 | I67: madison.navarro+415@demo-hoa.example | L67: P4-127 | O67: S-093 | P67: Y
A68: 416 | B68: 4 | C68: 16 | D68: 3BR | E68: 1978 | F68: Owner | G68: Sophia Alvarez | H68: (305) 555-1067 | I68: sophia.alvarez+416@demo-hoa.example | L68: P1-050 | M68: P2-090 | O68: S-157 | P68: Y
A69: 417 | B69: 4 | C69: 17 | D69: PH | E69: 3938 | F69: Owner | G69: James Castillo | H69: (305) 555-1068 | I69: james.castillo+417@demo-hoa.example | L69: P1-069 | M69: P3-082 | O69: S-085 | P69: Y
A70: 501 | B70: 5 | C70: 1 | D70: 1BR | E70: 916 | F70: Owner | G70: Lucas Flores | H70: (305) 555-1069 | I70: lucas.flores+501@demo-hoa.example | L70: P3-055 | P70: Y
A71: 502 | B71: 5 | C71: 2 | D71: 1BR | E71: 834 | F71: Owner | G71: Sophia Diaz | H71: (305) 555-1070 | I71: sophia.diaz+502@demo-hoa.example | L71: P4-123 | O71: S-099 | P71: Y
A72: 503 | B72: 5 | C72: 3 | D72: 1BR | E72: 935 | F72: Renter | G72: Isabella Martinez | H72: (305) 555-1071 | I72: isabella.martinez+503@demo-hoa.example | J72: Amelia Diaz | K72: 46444 | L72: P4-040 | P72: Y
A73: 504 | B73: 5 | C73: 4 | D73: 1BR | E73: 970 | F73: Owner | G73: Sebastian Rivera | H73: (305) 555-1072 | I73: sebastian.rivera+504@demo-hoa.example | L73: P2-282 | O73: S-071 | P73: Y
A74: 505 | B74: 5 | C74: 5 | D74: 1BR | E74: 868 | F74: Renter | G74: Sofia Sanchez | H74: (305) 555-1073 | I74: sofia.sanchez+505@demo-hoa.example | J74: Charlotte Cruz | K74: 46232 | L74: P5-012 | O74: S-149 | P74: Y
A75: 506 | B75: 5 | C75: 6 | D75: 1BR | E75: 911 | F75: Owner | G75: Elijah Morales | H75: (305) 555-1074 | I75: elijah.morales+506@demo-hoa.example | L75: P4-180 | O75: S-004 | P75: Y
A76: 507 | B76: 5 | C76: 7 | D76: 2BR | E76: 1284 | F76: Owner | G76: Abigail Navarro | H76: (305) 555-1075 | I76: abigail.navarro+507@demo-hoa.example | L76: P5-231 | M76: P3-225 | O76: S-296 | P76: N
A77: 508 | B77: 5 | C77: 8 | D77: 2BR | E77: 1393 | F77: Owner | G77: Lucas Diaz | H77: (305) 555-1076 | I77: lucas.diaz+508@demo-hoa.example | L77: P4-132 | M77: P3-149 | O77: S-260 | P77: N
A78: 509 | B78: 5 | C78: 9 | D78: 2BR | E78: 1311 | F78: Renter | G78: Harper Perez | H78: (305) 555-1077 | I78: harper.perez+509@demo-hoa.example | J78: Michael Delgado | K78: 46280 | L78: P4-062 | M78: P5-234 | P78: N
A79: 510 | B79: 5 | C79: 10 | D79: 2BR | E79: 1448 | F79: Renter | G79: Daniel Martinez | H79: (305) 555-1078 | I79: daniel.martinez+510@demo-hoa.example | J79: Madison Rodriguez | K79: 46309 | L79: P5-155 | O79: S-176 | P79: Y
A80: 511 | B80: 5 | C80: 11 | D80: 2BR | E80: 1413 | F80: Owner | G80: Daniel Cruz | H80: (305) 555-1079 | I80: daniel.cruz+511@demo-hoa.example | L80: P2-083 | P80: Y
A81: 512 | B81: 5 | C81: 12 | D81: 2BR | E81: 1390 | F81: Owner | G81: Amelia Chavez | H81: (305) 555-1080 | I81: amelia.chavez+512@demo-hoa.example | L81: P3-018 | O81: S-100 | P81: Y
A82: 513 | B82: 5 | C82: 13 | D82: 3BR | E82: 1748 | F82: Owner | G82: Isabella Vargas | H82: (305) 555-1081 | I82: isabella.vargas+513@demo-hoa.example | L82: P3-084 | M82: P4-036 | P82: Y
A83: 514 | B83: 5 | C83: 14 | D83: 3BR | E83: 2120 | F83: Owner | G83: Sofia Ramirez | H83: (305) 555-1082 | I83: sofia.ramirez+514@demo-hoa.example | L83: P2-241 | M83: P3-094 | N83: B-016 | P83: N
A84: 515 | B84: 5 | C84: 15 | D84: 3BR | E84: 2065 | F84: Owner | G84: Elijah Martinez | H84: (305) 555-1083 | I84: elijah.martinez+515@demo-hoa.example | L84: P5-061 | N84: B-090 | P84: N
A85: 516 | B85: 5 | C85: 16 | D85: 3BR | E85: 1747 | F85: Renter | G85: Lucas Sanchez | H85: (305) 555-1084 | I85: lucas.sanchez+516@demo-hoa.example | J85: Grace Navarro | K85: 46473 | L85: P2-102 | M85: P4-091 | N85: B-082 | O85: S-263 | P85: N
A86: 517 | B86: 5 | C86: 17 | D86: PH | E86: 3167 | F86: Renter | G86: Olivia Rodriguez | H86: (305) 555-1085 | I86: olivia.rodriguez+517@demo-hoa.example | J86: Isabella Ramos | K86: 46197 | L86: P4-054 | M86: P4-055 | P86: N
A87: 601 | B87: 6 | C87: 1 | D87: 1BR | E87: 958 | F87: Renter | G87: Sofia Romero | H87: (305) 555-1086 | I87: sofia.romero+601@demo-hoa.example | J87: Noah Gutierrez | K87: 46466 | L87: P1-135 | O87: S-113 | P87: N
A88: 602 | B88: 6 | C88: 2 | D88: 1BR | E88: 907 | F88: Owner | G88: Amelia Delgado | H88: (305) 555-1087 | I88: amelia.delgado+602@demo-hoa.example | L88: P4-094 | P88: Y
A89: 603 | B89: 6 | C89: 3 | D89: 1BR | E89: 916 | F89: Owner | G89: Charlotte Hernandez | H89: (305) 555-1088 | I89: charlotte.hernandez+603@demo-hoa.example | L89: P1-144 | P89: Y
A90: 604 | B90: 6 | C90: 4 | D90: 1BR | E90: 838 | F90: Owner | G90: Henry Castillo | H90: (305) 555-1089 | I90: henry.castillo+604@demo-hoa.example | L90: P2-261 | O90: S-005 | P90: Y
A91: 605 | B91: 6 | C91: 5 | D91: 1BR | E91: 843 | F91: Owner | G91: Amelia Lopez | H91: (305) 555-1090 | I91: amelia.lopez+605@demo-hoa.example | L91: P4-092 | O91: S-101 | P91: Y
A92: 606 | B92: 6 | C92: 6 | D92: 1BR | E92: 962 | F92: Owner | G92: James Chavez | H92: (305) 555-1091 | I92: james.chavez+606@demo-hoa.example | L92: P5-038 | O92: S-288 | P92: Y
A93: 607 | B93: 6 | C93: 7 | D93: 2BR | E93: 1186 | F93: Owner | G93: Noah Romero | H93: (305) 555-1092 | I93: noah.romero+607@demo-hoa.example | L93: P5-027 | P93: Y
A94: 608 | B94: 6 | C94: 8 | D94: 2BR | E94: 1374 | F94: Owner | G94: Amelia Ortiz | H94: (305) 555-1093 | I94: amelia.ortiz+608@demo-hoa.example | L94: P1-134 | M94: P1-095 | O94: S-092 | P94: Y
A95: 609 | B95: 6 | C95: 9 | D95: 2BR | E95: 1364 | F95: Renter | G95: Elijah Vargas | H95: (305) 555-1094 | I95: elijah.vargas+609@demo-hoa.example | J95: Alexander Sanchez | K95: 46338 | L95: P1-208 | M95: P4-220 | O95: S-279 | P95: N
A96: 610 | B96: 6 | C96: 10 | D96: 2BR | E96: 1348 | F96: Owner | G96: Ella Navarro | H96: (305) 555-1095 | I96: ella.navarro+610@demo-hoa.example | L96: P3-083 | P96: Y
A97: 611 | B97: 6 | C97: 11 | D97: 2BR | E97: 1425 | F97: Renter | G97: Olivia Flores | H97: (305) 555-1096 | I97: olivia.flores+611@demo-hoa.example | J97: Michael Mendoza | K97: 46440 | L97: P1-004 | P97: Y
A98: 612 | B98: 6 | C98: 12 | D98: 2BR | E98: 1366 | F98: Owner | G98: Logan Perez | H98: (305) 555-1097 | I98: logan.perez+612@demo-hoa.example | L98: P5-008 | P98: Y
A99: 613 | B99: 6 | C99: 13 | D99: 3BR | E99: 1948 | F99: Renter | G99: Henry Delgado | H99: (305) 555-1098 | I99: henry.delgado+613@demo-hoa.example | J99: Benjamin Alvarez | K99: 46339 | L99: P3-152 | O99: S-168 | P99: Y
A100: 614 | B100: 6 | C100: 14 | D100: 3BR | E100: 2109 | F100: Owner | G100: Charlotte Chavez | H100: (305) 555-1099 | I100: charlotte.chavez+614@demo-hoa.example | L100: P4-044 | M100: P5-023 | P100: Y
...

Sheet Accounts_AR
A1: Unit | B1: Account Holder | C1: Monthly Assessment | D1: Annual Assessment | E1: Special Assessment Active | F1: Special Assessment Balance | G1: Current Balance | H1: Last Payment Date | I1: Last Payment Amount | J1: Payment Method | K1: Last Assessment Due Date | L1: Days Past Due | M1: Delinquency Bucket | N1: Late Fees | O1: Payment Plan | P1: Autopay
A2: 101 | B2: Henry Delgado | C2: 725 | D2: =C2*12 -> 8700 | E2: Y | F2: 7947.67 | G2: 0 | H2: 46058 | I2: 584.81 | J2: Wire | K2: 46054 | L2: =IF(G2<=0,0,MAX(0,Assumptions!$B$3-K2)) -> 0 | M2: =IF(G2<=0,"Current",IF(L2<=30,"30 days",IF(L2<=60,"60 days",IF(L2<=90,"90 days","90+ days")))) -> Current | N2: 0 | O2: N | P2: N
A3: 102 | B3: Evelyn Gutierrez | C3: 725 | D3: =C3*12 -> 8700 | E3: N | F3: 0 | G3: 0 | H3: 46051 | I3: 657.02 | J3: Online Portal | K3: 46054 | L3: =IF(G3<=0,0,MAX(0,Assumptions!$B$3-K3)) -> 0 | M3: =IF(G3<=0,"Current",IF(L3<=30,"30 days",IF(L3<=60,"60 days",IF(L3<=90,"90 days","90+ days")))) -> Current | N3: 0 | O3: N | P3: Y
A4: 103 | B4: Mason Hernandez | C4: 725 | D4: =C4*12 -> 8700 | E4: N | F4: 0 | G4: 2275.09 | H4: 45984 | I4: 659.05 | J4: ACH | K4: 45964 | L4: =IF(G4<=0,0,MAX(0,Assumptions!$B$3-K4)) -> 0 | M4: =IF(G4<=0,"Current",IF(L4<=30,"30 days",IF(L4<=60,"60 days",IF(L4<=90,"90 days","90+ days")))) -> 30 days | N4: 0 | O4: N | P4: N
A5: 104 | B5: Charlotte Gutierrez | C5: 725 | D5: =C5*12 -> 8700 | E5: N | F5: 0 | G5: 0 | H5: 46061 | I5: 696.78 | J5: Online Portal | K5: 46054 | L5: =IF(G5<=0,0,MAX(0,Assumptions!$B$3-K5)) -> 0 | M5: =IF(G5<=0,"Current",IF(L5<=30,"30 days",IF(L5<=60,"60 days",IF(L5<=90,"90 days","90+ days")))) -> Current | N5: 0 | O5: N | P5: N
A6: 105 | B6: Emily Rivera | C6: 725 | D6: =C6*12 -> 8700 | E6: N | F6: 0 | G6: 0 | H6: 46030 | I6: 594.46 | J6: Check | K6: 46054 | L6: =IF(G6<=0,0,MAX(0,Assumptions!$B$3-K6)) -> 0 | M6: =IF(G6<=0,"Current",IF(L6<=30,"30 days",IF(L6<=60,"60 days",IF(L6<=90,"90 days","90+ days")))) -> Current | N6: 0 | O6: N | P6: N
A7: 106 | B7: Noah Rodriguez | C7: 725 | D7: =C7*12 -> 8700 | E7: Y | F7: 803.35 | G7: 0 | H7: 46058 | I7: 599.1 | J7: ACH | K7: 46054 | L7: =IF(G7<=0,0,MAX(0,Assumptions!$B$3-K7)) -> 0 | M7: =IF(G7<=0,"Current",IF(L7<=30,"30 days",IF(L7<=60,"60 days",IF(L7<=90,"90 days","90+ days")))) -> Current | N7: 0 | O7: N | P7: Y
A8: 107 | B8: Lucas Flores | C8: 890 | D8: =C8*12 -> 10680 | E8: N | F8: 0 | G8: 0 | H8: 46048 | I8: 851.87 | J8: Check | K8: 46054 | L8: =IF(G8<=0,0,MAX(0,Assumptions!$B$3-K8)) -> 0 | M8: =IF(G8<=0,"Current",IF(L8<=30,"30 days",IF(L8<=60,"60 days",IF(L8<=90,"90 days","90+ days")))) -> Current | N8: 0 | O8: N | P8: N
A9: 108 | B9: Abigail Ramirez | C9: 890 | D9: =C9*12 -> 10680 | E9: N | F9: 0 | G9: 25 | H9: 46063 | I9: 991.72 | J9: Credit Card | K9: 46054 | L9: =IF(G9<=0,0,MAX(0,Assumptions!$B$3-K9)) -> 0 | M9: =IF(G9<=0,"Current",IF(L9<=30,"30 days",IF(L9<=60,"60 days",IF(L9<=90,"90 days","90+ days")))) -> 30 days | N9: 0 | O9: N | P9: N
A10: 109 | B10: Evelyn Gomez | C10: 890 | D10: =C10*12 -> 10680 | E10: N | F10: 0 | G10: 0 | H10: 46067 | I10: 777.89 | J10: Online Portal | K10: 46054 | L10: =IF(G10<=0,0,MAX(0,Assumptions!$B$3-K10)) -> 0 | M10: =IF(G10<=0,"Current",IF(L10<=30,"30 days",IF(L10<=60,"60 days",IF(L10<=90,"90 days","90+ days")))) -> Current | N10: 0 | O10: N | P10: N
A11: 110 | B11: Charlotte Gomez | C11: 890 | D11: =C11*12 -> 10680 | E11: N | F11: 0 | G11: 25 | H11: 46063 | I11: 824.18 | J11: ACH | K11: 46054 | L11: =IF(G11<=0,0,MAX(0,Assumptions!$B$3-K11)) -> 0 | M11: =IF(G11<=0,"Current",IF(L11<=30,"30 days",IF(L11<=60,"60 days",IF(L11<=90,"90 days","90+ days")))) -> 30 days | N11: 0 | O11: N | P11: Y
A12: 111 | B12: Logan Rivera | C12: 890 | D12: =C12*12 -> 10680 | E12: N | F12: 0 | G12: 0 | H12: 46031 | I12: 880.96 | J12: Credit Card | K12: 46054 | L12: =IF(G12<=0,0,MAX(0,Assumptions!$B$3-K12)) -> 0 | M12: =IF(G12<=0,"Current",IF(L12<=30,"30 days",IF(L12<=60,"60 days",IF(L12<=90,"90 days","90+ days")))) -> Current | N12: 0 | O12: N | P12: Y
A13: 112 | B13: Madison Morales | C13: 890 | D13: =C13*12 -> 10680 | E13: N | F13: 0 | G13: 1048.65 | H13: 45916 | I13: 474.33 | J13: Wire | K13: 46024 | L13: =IF(G13<=0,0,MAX(0,Assumptions!$B$3-K13)) -> 0 | M13: =IF(G13<=0,"Current",IF(L13<=30,"30 days",IF(L13<=60,"60 days",IF(L13<=90,"90 days","90+ days")))) -> 30 days | N13: 0 | O13: N | P13: N
... A851: 5017 | B851: Jackson Vargas | C851: 1653 | D851: =C851*12 -> 19836 | E851: N | F851: 0 | G851: 0 | H851: 46034 | I851: 1702.32 | J851: Wire | K851: 46054 | L851: =IF(G851<=0,0,MAX(0,Assumptions!$B$3-K851)) -> 0 | M851: =IF(G851<=0,"Current",IF(L851<=30,"30 days",IF(L851<=60,"60 days",IF(L851<=90,"90 days","90+ days")))) -> Current | N851: 0 | O851: N | P851: N

Sheet Amenities_Parking
A1: Space ID | B1: Level | C1: Type | D1: Assigned Unit | E1: Notes
A2: P1-001 | B2: P1 | C2: Assigned | D2: 3810
A3: P1-002 | B3: P1 | C3: Guest
A4: P1-003 | B4: P1 | C4: Assigned | D4: 1006
A5: P1-004 | B5: P1 | C5: Assigned | D5: 611
A6: P1-005 | B6: P1 | C6: Assigned | D6: 4802
A7: P1-006 | B7: P1 | C7: Assigned | D7: 3516
A8: P1-007 | B8: P1 | C8: Valet
A9: P1-008 | B9: P1 | C9: Assigned | D9: 4412
A10: P1-009 | B10: P1 | C10: Assigned | D10: 715
A11: P1-010 | B11: P1 | C11: Assigned | D11: 210
A12: P1-011 | B12: P1 | C12: Assigned | D12: 2610
A13: P1-012 | B13: P1 | C13: Assigned | D13: 207
A14: P1-013 | B14: P1 | C14: Assigned | D14: 2805
A15: P1-014 | B15: P1 | C15: Valet
A16: P1-015 | B16: P1 | C16: Assigned | D16: 5012
A17: P1-016 | B17: P1 | C17: Assigned | D17: 311
A18: P1-017 | B18: P1 | C18: Assigned | D18: 4509
A19: P1-018 | B19: P1 | C19: Assigned | D19: 2517
A20: P1-019 | B20: P1 | C20: Assigned | D20: 1710
A21: P1-020 | B21: P1 | C21: Assigned | D21: 4604
A22: P1-021 | B22: P1 | C22: Assigned | D22: 3212
A23: P1-022 | B23: P1 | C23: Assigned | D23: 217
A24: P1-023 | B24: P1 | C24: Assigned | D24: 1307
A25: P1-024 | B25: P1 | C25: Guest
A26: P1-025 | B26: P1 | C26: Assigned | D26: 4207
A27: P1-026 | B27: P1 | C27: Assigned | D27: 3615
A28: P1-027 | B28: P1 | C28: Assigned | D28: 2903
A29: P1-028 | B29: P1 | C29: Assigned | D29: 3108
A30: P1-029 | B30: P1 | C30: Assigned | D30: 4110
A31: P1-030 | B31: P1 | C31: Assigned | D31: 3117
A32: P1-031 | B32: P1 | C32: Assigned | D32: 4812
A33: P1-032 | B33: P1 | C33: Assigned | D33: 3001
A34: P1-033 | B34: P1 | C34: Assigned | D34: 106
A35: P1-034 | B35: P1 | C35: Assigned | D35: 713
A36: P1-035 | B36: P1 | C36: Assigned | D36: 105
A37: P1-036 | B37: P1 | C37: Assigned | D37: 1413
... A40: P1-039 | B40: P1 | C40: Assigned | D40: 1211
A41: P1-040 | B41: P1 | C41: Valet
A42: P1-041 | B42: P1 | C42: Assigned | D42: 917
A43: P1-042 | B43: P1 | C43: Assigned | D43: 3002
A44: P1-043 | B44: P1 | C44: Assigned | D44: 2810
A45: P1-044 | B45: P1 | C45: Assigned | D45: 5015
A46: P1-045 | B46: P1 | C46: Assigned | D46: 1016
A47: P1-046 | B47: P1 | C47: Assigned | D47: 4012
A48: P1-047 | B48: P1 | C48: Assigned | D48: 2405
A49: P1-048 | B49: P1 | C49: Assigned | D49: 3615
A50: P1-049 | B50: P1 | C50: Assigned | D50: 807
A51: P1-050 | B51: P1 | C51: Assigned | D51: 416
A52: P1-051 | B52: P1 | C52: Assigned | D52: 4307
A53: P1-052 | B53: P1 | C53: Guest
A54: P1-053 | B54: P1 | C54: Assigned | D54: 2313
A55: P1-054 | B55: P1 | C55: Assigned | D55: 3007
A56: P1-055 | B56: P1 | C56: Guest
A57: P1-056 | B57: P1 | C57: Assigned | D57: 2404
A58: P1-057 | B58: P1 | C58: Assigned | D58: 808
A59: P1-058 | B59: P1 | C59: Assigned | D59: 615
A60: P1-059 | B60: P1 | C60: Assigned | D60: 2102
A61: P1-060 | B61: P1 | C61: Assigned | D61: 1707
A62: P1-061 | B62: P1 | C62: Assigned | D62: 1511
A63: P1-062 | B63: P1 | C63: Guest
A64: P1-063 | B64: P1 | C64: Assigned | D64: 1603
A65: P1-064 | B65: P1 | C65: Assigned | D65: 3217
A66: P1-065 | B66: P1 | C66: Assigned | D66: 5009
A67: P1-066 | B67: P1 | C67: Guest
A68: P1-067 | B68: P1 | C68: Assigned | D68: 2309
A69: P1-068 | B69: P1 | C69: Assigned | D69: 1608
A70: P1-069 | B70: P1 | C70: Assigned | D70: 417
A71: P1-070 | B71: P1 | C71: Assigned | D71: 1414
A72: P1-071 | B72: P1 | C72: Assigned | D72: 3004
A73: P1-072 | B73: P1 | C73: Assigned | D73: 4201
A74: P1-073 | B74: P1 | C74: Assigned | D74: 2014
A75: P1-074 | B75: P1 | C75: Assigned | D75: 4403
A76: P1-075 | B76: P1 | C76: Assigned | D76: 3612
A77: P1-076 | B77: P1 | C77: Assigned | D77: 2308
A78: P1-077 | B78: P1 | C78: Assigned | D78: 2207
A79: P1-078 | B79: P1 | C79: Assigned | D79: 2816
... A89: P1-088 | B89: P1 | C89: Assigned | D89: 2608
A90: P1-089 | B90: P1 | C90: Guest
A91: P1-090 | B91: P1 | C91: Assigned | D91: 1814
A92: P1-091 | B92: P1 | C92: Assigned | D92: 4412
A93: P1-092 | B93: P1 | C93: Assigned | D93: 1108
A94: P1-093 | B94: P1 | C94: Assigned | D94: 1809
A95: P1-094 | B95: P1 | C95: Valet
A96: P1-095 | B96: P1 | C96: Assigned | D96: 608
A97: P1-096 | B97: P1 | C97: Assigned | D97: 3706
A98: P1-097 | B98: P1 | C98: Valet
A99: P1-098 | B99: P1 | C99: Assigned | D99: 1416
A100: P1-099 | B100: P1 | C100: Assigned | D100: 910
A101: P1-100 | B101: P1 | C101: Assigned | D101: 211
A102: P1-101 | B102: P1 | C102: Assigned | D102: 217
A103: P1-102 | B103: P1 | C103: Assigned | D103: 2212
A104: P1-103 | B104: P1 | C104: Assigned | D104: 4708
A105: P1-104 | B105: P1 | C105: Assigned | D105: 4813
A106: P1-105 | B106: P1 | C106: Assigned | D106: 4415
A107: P1-106 | B107: P1 | C107: Assigned | D107: 2317
A108: P1-107 | B108: P1 | C108: Assigned | D108: 711
A109: P1-108 | B109: P1 | C109: Assigned | D109: 409
A110: P1-109 | B110: P1 | C110: Assigned | D110: 2802
... A115: P1-114 | B115: P1 | C115: Assigned | D115: 916
...

Sheet Amenities_BoatSlips
A1: Slip ID | B1: Assigned Unit | C1: Max Length | D1: Monthly Fee | E1: Waitlist
A2: B-001 | B2: 812 | C2: 45 | D2: 707.31 | E2: N
A3: B-002 | B3: 2617 | C3: 45 | D3: 514.02 | E3: N
A4: B-003 | B4: 1102 | C4: 32 | D4: 808.83 | E4: N
A5: B-004 | B5: 2010 | C5: 45 | D5: 845.25 | E5: N
A6: B-005 | B6: 2213 | C6: 32 | D6: 543.76 | E6: N
A7: B-006 | B7: 2908 | C7: 28 | D7: 624.77 | E7: N
A8: B-007 | B8: 4302 | C8: 50 | D8: 937.44 | E8: N
A9: B-008 | B9: 813 | C9: 45 | D9: 769.1 | E9: N
A10: B-009 | B10: 4109 | C10: 50 | D10: 601.28 | E10: N
A11: B-010 | B11: 2305 | C11: 30 | D11: 481.45 | E11: N
A12: B-011 | B12: 3615 | C12: 28 | D12: 434.99 | E12: N
A13: B-012 | B13: 2603 | C13: 40 | D13: 539.03 | E13: N
... A21: B-020 | B21: 3709 | C21: 40 | D21: 691.01 | E21: N
A22: B-021 | C22: 28 | D22: 627.94 | E22: N
A23: B-022 | B23: 3207 | C23: 35 | D23: 677.37 | E23: N
A24: B-023 | B24: 413 | C24: 28 | D24: 690.95 | E24: N
A25: B-024 | B25: 2709 | C25: 30 | D25: 764.79 | E25: N
A26: B-025 | B26: 3301 | C26: 32 | D26: 635.04 | E26: N
A27: B-026 | B27: 2017 | C27: 32 | D27: 530.66 | E27: N
A28: B-027 | B28: 108 | C28: 32 | D28: 673.97 | E28: N
A29: B-028 | B29: 2816 | C29: 32 | D29: 636.82 | E29: N
A30: B-029 | B30: 406 | C30: 35 | D30: 504.51 | E30: N
A31: B-030 | B31: 115 | C31: 40 | D31: 918.52 | E31: N
A32: B-031 | B32: 1801 | C32: 32 | D32: 474.66 | E32: N
A33: B-032 | B33: 2509 | C33: 28 | D33: 617.69 | E33: N
A34: B-033 | B34: 3713 | C34: 50 | D34: 957.07 | E34: N
... A57: B-056 | B57: 2308 | C57: 30 | D57: 545.42 | E57: N
A58: B-057 | C58: 32 | D58: 740.67 | E58: Y
A59: B-058 | B59: 2510 | C59: 40 | D59: 877.46 | E59: N
A60: B-059 | B60: 911 | C60: 40 | D60: 567.51 | E60: N
A61: B-060 | B61: 2901 | C61: 40 | D61: 917.36 | E61: N
A62: B-061 | B62: 1817 | C62: 32 | D62: 605.49 | E62: N
A63: B-062 | B63: 816 | C63: 35 | D63: 775.27 | E63: N
A64: B-063 | B64: 2604 | C64: 35 | D64: 781.13 | E64: N
A65: B-064 | B65: 1610 | C65: 35 | D65: 534.96 | E65: N
A66: B-065 | B66: 1906 | C66: 50 | D66: 737.71 | E66: N
A67: B-066 | B67: 3213 | C67: 30 | D67: 838.4 | E67: N
A68: B-067 | C68: 40 | D68: 629 | E68: N
A69: B-068 | C69: 40 | D69: 856.11 | E69: N
A70: B-069 | B70: 2211 | C70: 40 | D70: 810.86 | E70: N
A71: B-070 | B71: 3407 | C71: 28 | D71: 460.72 | E71: N
A72: B-071 | B72: 3113 | C72: 35 | D72: 717.71 | E72: N
A73: B-072 | B73: 4009 | C73: 50 | D73: 959.79 | E73: N
A74: B-073 | B74: 2803 | C74: 35 | D74: 432.28 | E74: N
A75: B-074 | B75: 1311 | C75: 40 | D75: 553.81 | E75: N
A76: B-075 | B76: 1104 | C76: 28 | D76: 451.99 | E76: N
A77: B-076 | B77: 3316 | C77: 32 | D77: 524.08 | E77: N
A78: B-077 | B78: 4305 | C78: 40 | D78: 693.54 | E78: N
A79: B-078 | B79: 3701 | C79: 40 | D79: 903.57 | E79: N
A80: B-079 | C80: 45 | D80: 564.44 | E80: N
A81: B-080 | B81: 4015 | C81: 50 | D81: 706.27 | E81: N
A82: B-081 | B82: 4216 | C82: 40 | D82: 922.84 | E82: N
A83: B-082 | B83: 516 | C83: 40 | D83: 586.44 | E83: N
A84: B-083 | B84: 2501 | C84: 30 | D84: 404.34 | E84: N
A85: B-084 | B85: 3002 | C85: 45 | D85: 868.56 | E85: N
A86: B-085 | B86: 3117 | C86: 28 | D86: 438.99 | E86: N
A87: B-086 | B87: 3908 | C87: 32 | D87: 595.64 | E87: N
A88: B-087 | B88: 3814 | C88: 50 | D88: 895.9 | E88: N
A89: B-088 | B89: 3003 | C89: 28 | D89: 635.29 | E89: N
A90: B-089 | B90: 2201 | C90: 30 | D90: 408.89 | E90: N
A91: B-090 | B91: 515 | C91: 28 | D91: 501.02 | E91: N
A92: B-091 | C92: 40 | D92: 703.25 | E92: N
A93: B-092 | B93: 1006 | C93: 45 | D93: 931.29 | E93: N
A94: B-093 | B94: 3104 | C94: 40 | D94: 710.14 | E94: N
A95: B-094 | B95: 1805 | C95: 50 | D95: 821.24 | E95: N
A96: B-095 | C96: 32 | D96: 731.71 | E96: N
A97: B-096 | B97: 3114 | C97: 45 | D97: 845.85 | E97: N

Sheet Vendors
A1: Vendor | B1: Category | C1: Primary Contact | D1: Phone | E1: Email | F1: Notes
A2: Seaside Group | B2: Pool | C2: James Perez | D2: (305) 555-3001 | E2: dispatch01@vendors.demo-hoa.example | F2: Preferred vendor
A3: BlueWave Maintenance | B3: Landscaping | C3: Sebastian Martinez | D3: (305) 555-3002 | E3: dispatch02@vendors.demo-hoa.example | F3: 24/7 on-call
A4: Biscayne Services | B4: Security | C4: Mason Ramirez | D4: (305) 555-3003 | E4: dispatch03@vendors.demo-hoa.example | F4: Requires escort
A5: BlueWave Services | B5: General Contractor | C5: Jackson Delgado | D5: (305) 555-3004 | E5: dispatch04@vendors.demo-hoa.example | F5: After-hours surcharge applies
A6: Seaside Services | B6: Fire/Life Safety | C6: Noah Gomez | D6: (305) 555-3005 | E6: dispatch05@vendors.demo-hoa.example | F6: Preferred vendor
A7: Biscayne Group | B7: General Contractor | C7: Grace Cruz | D7: (305) 555-3006 | E7: dispatch06@vendors.demo-hoa.example | F7: 24/7 on-call
A8: Atlantic Systems | B8: General Contractor | C8: Ethan Suarez | D8: (305) 555-3007 | E8: dispatch07@vendors.demo-hoa.example
A9: SunCoast Group | B9: Cleaning | C9: Daniel Rodriguez | D9: (305) 555-3008 | E9: dispatch08@vendors.demo-hoa.example | F9: 24/7 on-call
A10: Seaside Systems | B10: Fire/Life Safety | C10: Amelia Castillo | D10: (305) 555-3009 | E10: dispatch09@vendors.demo-hoa.example
A11: SunCoast Systems | B11: HVAC | C11: Alexander Ruiz | D11: (305) 555-3010 | E11: dispatch10@vendors.demo-hoa.example | F11: Preferred vendor
A12: Atlantic Maintenance | B12: Landscaping | C12: Elijah Hernandez | D12: (305) 555-3011 | E12: dispatch11@vendors.demo-hoa.example | F12: Preferred vendor
A13: BlueWave Maintenance | B13: Fire/Life Safety | C13: Noah Vargas | D13: (305) 555-3012 | E13: dispatch12@vendors.demo-hoa.example | F13: 24/7 on-call
A14: Biscayne Contracting | B14: HVAC | C14: Emily Gonzalez | D14: (305) 555-3013 | E14: dispatch13@vendors.demo-hoa.example
A15: Biscayne Services | B15: Elevator | C15: Ethan Lopez | D15: (305) 555-3014 | E15: dispatch14@vendors.demo-hoa.example
A16: BlueWave Contracting | B16: Landscaping | C16: Harper Suarez | D16: (305) 555-3015 | E16: dispatch15@vendors.demo-hoa.example
A17: Biscayne Services | B17: Plumbing | C17: Alexander Suarez | D17: (305) 555-3016 | E17: dispatch16@vendors.demo-hoa.example
A18: BlueWave Services | B18: Plumbing | C18: Mia Diaz | D18: (305) 555-3017 | E18: dispatch17@vendors.demo-hoa.example | F18: Requires escort
A19: Atlantic Systems | B19: Electrical | C19: Liam Lopez | D19: (305) 555-3018 | E19: dispatch18@vendors.demo-hoa.example | F19: After-hours surcharge applies
A20: BlueWave Services | B20: Fire/Life Safety | C20: Sophia Romero | D20: (305) 555-3019 | E20: dispatch19@vendors.demo-hoa.example | F20: COI on file
A21: BlueWave Group | B21: Pool | C21: Madison Morales | D21: (305) 555-3020 | E21: dispatch20@vendors.demo-hoa.example | F21: Preferred vendor
A22: Biscayne Maintenance | B22: Elevator | C22: Liam Flores | D22: (305) 555-3021 | E22: dispatch21@vendors.demo-hoa.example | F22: After-hours surcharge applies
A23: Biscayne Contracting | B23: Landscaping | C23: Olivia Sanchez | D23: (305) 555-3022 | E23: dispatch22@vendors.demo-hoa.example | F23: After-hours surcharge applies
A24: Atlantic Group | B24: Electrical | C24: Harper Castillo | D24: (305) 555-3023 | E24: dispatch23@vendors.demo-hoa.example
A25: Coral Solutions | B25: Pool | C25: Mia Gonzalez | D25: (305) 555-3024 | E25: dispatch24@vendors.demo-hoa.example | F25: COI on file
A26: Biscayne Services | B26: Plumbing | C26: Mason Rodriguez | D26: (305) 555-3025 | E26: dispatch25@vendors.demo-hoa.example | F26: After-hours surcharge applies
A27: BlueWave Contracting | B27: Pool | C27: Sophia Cruz | D27: (305) 555-3026 | E27: dispatch26@vendors.demo-hoa.example | F27: COI on file
A28: Coral Services | B28: General Contractor | C28: Daniel Rivera | D28: (305) 555-3027 | E28: dispatch27@vendors.demo-hoa.example | F28: Preferred vendor
A29: Biscayne Maintenance | B29: Security | C29: Charlotte Gonzalez | D29: (305) 555-3028 | E29: dispatch28@vendors.demo-hoa.example | F29: 24/7 on-call
A30: Coral Maintenance | B30: Elevator | C30: Sofia Navarro | D30: (305) 555-3029 | E30: dispatch29@vendors.demo-hoa.example | F30: COI on file
A31: Seaside Group | B31: Landscaping | C31: Ella Delgado | D31: (305) 555-3030 | E31: dispatch30@vendors.demo-hoa.example | F31: 24/7 on-call

Sheet Work_Orders
A1: Work Order ID | B1: Opened | C1: Unit | D1: Category | E1: Priority | F1: Status | G1: Vendor | H1: Description | I1: ETA
A2: WO-20260001 | B2: 45972 | D2: Common Area | E2: High | F2: Open | G2: Biscayne Contracting | H2: Pool pump noise | I2: 45978
A3: WO-20260002 | B3: 45976 | D3: Common Area | E3: Low | F3: Open | G3: BlueWave Contracting | H3: Lobby HVAC warm | I3: 45982
A4: WO-20260003 | B4: 46040 | C4: 2211 | D4: Plumbing | E4: Medium | F4: In Progress | G4: Biscayne Contracting | H4: Toilet running continuously | I4: 46046
A5: WO-20260004 | B5: 46048 | D5: Common Area | E5: Low | F5: Awaiting Vendor | G5: Seaside Services | H5: Lobby HVAC warm | I5: 46054
A6: WO-20260005 | B6: 46014 | D6: Common Area | E6: Low | F6: Open | G6: SunCoast Group | H6: Hallway lighting outage | I6: 46024
A7: WO-20260006 | B7: 46068 | C7: 3806 | D7: Plumbing | E7: Low | F7: Awaiting Vendor | G7: Biscayne Services | H7: Shower drain slow | I7: 46083
A8: WO-20260007 | B8: 45965 | D8: Elevator | E8: Low | F8: Closed | G8: BlueWave Services | H8: Elevator #2 slow leveling
A9: WO-20260008 | B9: 46032 | C9: 1010 | D9: HVAC | E9: High | F9: Awaiting Vendor | G9: Biscayne Maintenance | H9: AC not cooling below 76°F | I9: 46041
A10: WO-20260009 | B10: 45986 | D10: Common Area | E10: Low | F10: Open | G10: BlueWave Group | H10: Pool pump noise | I10: 46000
A11: WO-20260010 | B11: 46012 | C11: 2804 | D11: Elevator | E11: Low | F11: Closed | G11: SunCoast Systems | H11: Elevator #2 slow leveling
A12: WO-20260011 | B12: 46028 | C12: 4114 | D12: Electrical | E12: High | F12: In Progress | G12: SunCoast Systems | H12: GFCI reset needed | I12: 46035
A13: WO-20260012 | B13: 46044 | C13: 707 | D13: HVAC | E13: Low | F13: Closed | G13: BlueWave Contracting | H13: Filter replacement request
A14: WO-20260013 | B14: 46075 | C14: 3408 | D14: Plumbing | E14: Low | F14: Open | G14: BlueWave Contracting | H14: Intermittent leak under sink | I14: 46078
A15: WO-20260014 | B15: 46049 | C15: 4507 | D15: Plumbing | E15: High | F15: Awaiting Vendor | G15: BlueWave Services | H15: Shower drain slow | I15: 46063
A16: WO-20260015 | B16: 46040 | D16: Common Area | E16: Low | F16: In Progress | G16: Atlantic Systems | H16: Lobby HVAC warm | I16: 46058
A17: WO-20260016 | B17: 46063 | D17: Common Area | E17: Medium | F17: Open | G17: Seaside Group | H17: Lobby HVAC warm | I17: 46075
A18: WO-20260017 | B18: 45985 | C18: 602 | D18: Plumbing | E18: Low | F18: Open | G18: BlueWave Contracting | H18: Intermittent leak under sink | I18: 45994
A19: WO-20260018 | B19: 46069 | C19: 1414 | D19: Electrical | E19: Low | F19: Closed | G19: Coral Services | H19: Outlet not working
A20: WO-20260019 | B20: 46029 | C20: 3011 | D20: Common Area | E20: Low | F20: Closed | G20: Biscayne Group | H20: Lobby HVAC warm
A21: WO-20260020 | B21: 45985 | C21: 201 | D21: Plumbing | E21: Medium | F21: Open | G21: Atlantic Systems | H21: Toilet running continuously | I21: 46001
A22: WO-20260021 | B22: 46021 | D22: Common Area | E22: Medium | F22: Open | G22: Atlantic Systems | H22: Lobby HVAC warm | I22: 46033
A23: WO-20260022 | B23: 46050 | C23: 4714 | D23: Common Area | E23: Low | F23: In Progress | G23: Coral Services | H23: Hallway lighting outage | I23: 46060
A24: WO-20260023 | B24: 45968 | C24: 2413 | D24: Electrical | E24: Medium | F24: Open | G24: BlueWave Maintenance | H24: Breaker tripping in kitchen | I24: 45986
A25: WO-20260024 | B25: 46045 | D25: Common Area | E25: Medium | F25: Open | G25: Seaside Systems | H25: Hallway lighting outage | I25: 46060
A26: WO-20260025 | B26: 46021 | C26: 2016 | D26: Plumbing | E26: Medium | F26: Open | G26: Biscayne Services | H26: Intermittent leak under sink | I26: 46024
A27: WO-20260026 | B27: 46018 | D27: Elevator | E27: Low | F27: In Progress | G27: Seaside Group | H27: Door sensor issue | I27: 46038
A28: WO-20260027 | B28: 46045 | C28: 3405 | D28: Electrical | E28: Low | F28: Awaiting Vendor | G28: Biscayne Services | H28: Outlet not working | I28: 46065
A29: WO-20260028 | B29: 46075 | C29: 4104 | D29: HVAC | E29: Urgent | F29: Open | G29: BlueWave Contracting | H29: Condensation near air handler | I29: 46078
A30: WO-20260029 | B30: 46043 | D30: Elevator | E30: High | F30: In Progress | G30: Coral Services | H30: Service mode active unexpectedly | I30: 46057
A31: WO-20260030 | B31: 45975 | C31: 3909 | D31: Elevator | E31: Low | F31: Open | G31: BlueWave Contracting | H31: Service mode active unexpectedly | I31: 45980
A32: WO-20260031 | B32: 45971 | C32: 3706 | D32: HVAC | E32: Medium | F32: In Progress | G32: Biscayne Services | H32: Filter replacement request | I32: 45976
A33: WO-20260032 | B33: 46056 | C33: 1805 | D33: Plumbing | E33: Urgent | F33: In Progress | G33: BlueWave Services | H33: Toilet running continuously | I33: 46065
A34: WO-20260033 | B34: 46046 | C34: 2706 | D34: Common Area | E34: Low | F34: Awaiting Vendor | G34: BlueWave Services | H34: Pool pump noise | I34: 46066
A35: WO-20260034 | B35: 46003 | C35: 2715 | D35: Common Area | E35: High | F35: Open | G35: Coral Services | H35: Pool pump noise | I35: 46010
A36: WO-20260035 | B36: 45962 | C36: 4014 | D36: Electrical | E36: Low | F36: Open | G36: BlueWave Maintenance | H36: GFCI reset needed | I36: 45981
A37: WO-20260036 | B37: 45967 | C37: 607 | D37: Plumbing | E37: Medium | F37: Closed | G37: Biscayne Contracting | H37: Intermittent leak under sink
A38: WO-20260037 | B38: 45995 | D38: Common Area | E38: Low | F38: Closed | G38: Seaside Group | H38: Lobby HVAC warm
A39: WO-20260038 | B39: 46045 | C39: 4305 | D39: HVAC | E39: High | F39: Awaiting Vendor | G39: BlueWave Group | H39: Filter replacement request | I39: 46051
A40: WO-20260039 | B40: 45961 | C40: 2714 | D40: Plumbing | E40: Urgent | F40: Awaiting Vendor | G40: Atlantic Systems | H40: Toilet running continuously | I40: 45979
A41: WO-20260040 | B41: 46072 | C41: 3316 | D41: Common Area | E41: High | F41: Closed | G41: SunCoast Systems | H41: Garage gate sensor misaligned
A42: WO-20260041 | B42: 46055 | D42: Common Area | E42: High | F42: In Progress | G42: BlueWave Services | H42: Garage gate sensor misaligned | I42: 46075
A43: WO-20260042 | B43: 46019 | D43: Common Area | E43: High | F43: In Progress | G43: BlueWave Maintenance | H43: Lobby HVAC warm | I43: 46029
A44: WO-20260043 | B44: 46006 | C44: 2910 | D44: Plumbing | E44: Low | F44: Awaiting Vendor | G44: Coral Services | H44: Low water pressure in master bath | I44: 46014
A45: WO-20260044 | B45: 46027 | D45: Elevator | E45: Medium | F45: Closed | G45: Biscayne Contracting | H45: Elevator #2 slow leveling
A46: WO-20260045 | B46: 45956 | C46: 3102 | D46: Plumbing | E46: Medium | F46: Awaiting Vendor | G46: BlueWave Contracting | H46: Low water pressure in master bath | I46: 45977
A47: WO-20260046 | B47: 45990 | C47: 3107 | D47: Electrical | E47: Low | F47: Awaiting Vendor | G47: Biscayne Contracting | H47: GFCI reset needed | I47: 45993
A48: WO-20260047 | B48: 46041 | C48: 2207 | D48: Plumbing | E48: Low | F48: Open | G48: Coral Maintenance | H48: Intermittent leak under sink | I48: 46061
A49: WO-20260048 | B49: 46021 | C49: 2613 | D49: Plumbing | E49: Low | F49: Closed | G49: Biscayne Maintenance | H49: Low water pressure in master bath
A50: WO-20260049 | B50: 46053 | C50: 4111 | D50: Electrical | E50: High | F50: Awaiting Vendor | G50: Atlantic Systems | H50: Light fixture flickering | I50: 46065
A51: WO-20260050 | B51: 45983 | C51: 708 | D51: HVAC | E51: High | F51: In Progress | G51: BlueWave Contracting | H51: Filter replacement request | I51: 45990
A52: WO-20260051 | B52: 46038 | C52: 2607 | D52: Elevator | E52: Medium | F52: In Progress | G52: BlueWave Group | H52: Service mode active unexpectedly | I52: 46052
A53: WO-20260052 | B53: 46006 | C53: 1617 | D53: HVAC | E53: High | F53: In Progress | G53: Seaside Systems | H53: Filter replacement request | I53: 46024
A54: WO-20260053 | B54: 46036 | C54: 2713 | D54: Plumbing | E54: Low | F54: Awaiting Vendor | G54: BlueWave Services | H54: Shower drain slow | I54: 46042
A55: WO-20260054 | B55: 46055 | D55: Common Area | E55: High | F55: Closed | G55: Biscayne Services | H55: Pool pump noise
A56: WO-20260055 | B56: 46006 | C56: 101 | D56: Electrical | E56: Medium | F56: Awaiting Vendor | G56: BlueWave Contracting | H56: Light fixture flickering | I56: 46016
A57: WO-20260056 | B57: 46007 | C57: 4217 | D57: HVAC | E57: Medium | F57: Awaiting Vendor | G57: Coral Maintenance | H57: Filter replacement request | I57: 46013
A58: WO-20260057 | B58: 46042 | C58: 1002 | D58: HVAC | E58: Urgent | F58: Closed | G58: BlueWave Contracting | H58: AC not cooling below 76°F
A59: WO-20260058 | B59: 46021 | C59: 414 | D59: Plumbing | E59: Low | F59: Open | G59: Coral Services | H59: Intermittent leak under sink | I59: 46041
A60: WO-20260059 | B60: 45961 | C60: 2210 | D60: Common Area | E60: Medium | F60: Closed | G60: Biscayne Maintenance | H60: Garage gate sensor misaligned
A61: WO-20260060 | B61: 45970 | C61: 709 | D61: Common Area | E61: Low | F61: In Progress | G61: Biscayne Services | H61: Lobby HVAC warm | I61: 45982
A62: WO-20260061 | B62: 46052 | D62: Common Area | E62: Low | F62: Awaiting Vendor | G62: BlueWave Services | H62: Hallway lighting outage | I62: 46064
A63: WO-20260062 | B63: 45976 | D63: Common Area | E63: Low | F63: Closed | G63: Seaside Systems | H63: Pool pump noise
A64: WO-20260063 | B64: 46012 | C64: 809 | D64: Plumbing | E64: Medium | F64: In Progress | G64: Biscayne Maintenance | H64: Intermittent leak under sink | I64: 46020
A65: WO-20260064 | B65: 45986 | C65: 212 | D65: HVAC | E65: High | F65: In Progress | G65: Biscayne Maintenance | H65: AC not cooling below 76°F | I65: 46003
A66: WO-20260065 | B66: 45979 | C66: 4601 | D66: Common Area | E66: Low | F66: In Progress | G66: Atlantic Group | H66: Pool pump noise | I66: 46000
A67: WO-20260066 | B67: 46007 | D67: Elevator | E67: Low | F67: In Progress | G67: Seaside Group | H67: Elevator #2 slow leveling | I67: 46021
A68: WO-20260067 | B68: 46016 | D68: Common Area | E68: Low | F68: In Progress | G68: Biscayne Services | H68: Lobby HVAC warm | I68: 46025
A69: WO-20260068 | B69: 45968 | C69: 1203 | D69: HVAC | E69: High | F69: Awaiting Vendor | G69: Seaside Systems | H69: Filter replacement request | I69: 45989
A70: WO-20260069 | B70: 45991 | C70: 4909 | D70: Electrical | E70: High | F70: Awaiting Vendor | G70: BlueWave Services | H70: GFCI reset needed | I70: 46012
A71: WO-20260070 | B71: 46005 | C71: 3109 | D71: Electrical | E71: Low | F71: In Progress | G71: Coral Maintenance | H71: Breaker tripping in kitchen | I71: 46017
A72: WO-20260071 | B72: 46032 | C72: 4907 | D72: Elevator | E72: Medium | F72: Open | G72: BlueWave Group | H72: Call button intermittent | I72: 46053
A73: WO-20260072 | B73: 45989 | C73: 4207 | D73: Plumbing | E73: High | F73: Closed | G73: SunCoast Group | H73: Shower drain slow
A74: WO-20260073 | B74: 45962 | D74: Common Area | E74: Low | F74: Open | G74: Biscayne Contracting | H74: Lobby HVAC warm | I74: 45971
A75: WO-20260074 | B75: 45969 | C75: 3408 | D75: Elevator | E75: High | F75: Open | G75: Atlantic Maintenance | H75: Call button intermittent | I75: 45984
A76: WO-20260075 | B76: 45985 | D76: Elevator | E76: Medium | F76: In Progress | G76: BlueWave Group | H76: Elevator #2 slow leveling | I76: 45999
A77: WO-20260076 | B77: 46013 | C77: 209 | D77: Plumbing | E77: Medium | F77: Awaiting Vendor | G77: SunCoast Systems | H77: Low water pressure in master bath | I77: 46024
A78: WO-20260077 | B78: 46008 | D78: Common Area | E78: Low | F78: Closed | G78: Biscayne Contracting | H78: Pool pump noise
A79: WO-20260078 | B79: 45975 | C79: 3717 | D79: Common Area | E79: Medium | F79: In Progress | G79: BlueWave Maintenance | H79: Pool pump noise | I79: 45990
A80: WO-20260079 | B80: 46042 | C80: 5007 | D80: Plumbing | E80: High | F80: In Progress | G80: Biscayne Services | H80: Toilet running continuously | I80: 46059
A81: WO-20260080 | B81: 45979 | C81: 3307 | D81: Electrical | E81: High | F81: Awaiting Vendor | G81: BlueWave Contracting | H81: Outlet not working | I81: 45991
A82: WO-20260081 | B82: 46047 | C82: 3109 | D82: Plumbing | E82: High | F82: Open | G82: Seaside Services | H82: Low water pressure in master bath | I82: 46060
A83: WO-20260082 | B83: 46042 | C83: 4804 | D83: Common Area | E83: Low | F83: Awaiting Vendor | G83: Biscayne Services | H83: Hallway lighting outage | I83: 46054
A84: WO-20260083 | B84: 45986 | C84: 710 | D84: HVAC | E84: Low | F84: In Progress | G84: BlueWave Group | H84: Thermostat unresponsive | I84: 45995
A85: WO-20260084 | B85: 45957 | C85: 4215 | D85: Plumbing | E85: High | F85: In Progress | G85: Biscayne Maintenance | H85: Low water pressure in master bath | I85: 45962
A86: WO-20260085 | B86: 46053 | C86: 1116 | D86: Plumbing | E86: Urgent | F86: Closed | G86: Biscayne Services | H86: Shower drain slow
A87: WO-20260086 | B87: 45987 | D87: Elevator | E87: Low | F87: In Progress | G87: Biscayne Services | H87: Service mode active unexpectedly | I87: 45989
A88: WO-20260087 | B88: 46062 | C88: 1716 | D88: Plumbing | E88: Medium | F88: Open | G88: BlueWave Maintenance | H88: Toilet running continuously | I88: 46081
A89: WO-20260088 | B89: 45973 | C89: 2407 | D89: Electrical | E89: Urgent | F89: Open | G89: Coral Maintenance | H89: Breaker tripping in kitchen | I89: 45978
A90: WO-20260089 | B90: 46015 | C90: 2917 | D90: Elevator | E90: Medium | F90: Closed | G90: Seaside Services | H90: Call button intermittent
A91: WO-20260090 | B91: 45964 | C91: 3514 | D91: Plumbing | E91: Medium | F91: Closed | G91: BlueWave Contracting | H91: Intermittent leak under sink
A92: WO-20260091 | B92: 45956 | D92: Common Area | E92: Urgent | F92: In Progress | G92: Seaside Systems | H92: Garage gate sensor misaligned | I92: 45971
A93: WO-20260092 | B93: 46066 | C93: 712 | D93: Plumbing | E93: High | F93: Open | G93: BlueWave Services | H93: Toilet running continuously | I93: 46075
A94: WO-20260093 | B94: 45981 | D94: Common Area | E94: Low | F94: In Progress | G94: BlueWave Services | H94: Hallway lighting outage | I94: 46000
A95: WO-20260094 | B95: 46069 | C95: 2202 | D95: Electrical | E95: Urgent | F95: Awaiting Vendor | G95: BlueWave Maintenance | H95: Outlet not working | I95: 46087
A96: WO-20260095 | B96: 46053 | C96: 808 | D96: HVAC | E96: Medium | F96: Awaiting Vendor | G96: SunCoast Group | H96: Thermostat unresponsive | I96: 46063
A97: WO-20260096 | B97: 46029 | C97: 1703 | D97: Common Area | E97: Low | F97: Awaiting Vendor | G97: Biscayne Services | H97: Pool pump noise | I97: 46040
A98: WO-20260097 | B98: 45992 | C98: 4005 | D98: HVAC | E98: Medium | F98: Awaiting Vendor | G98: Biscayne Maintenance | H98: Condensation near air handler | I98: 45996
A99: WO-20260098 | B99: 46061 | C99: 1212 | D99: Plumbing | E99: Low | F99: Awaiting Vendor | G99: BlueWave Contracting | H99: Toilet running continuously | I99: 46080
A100: WO-20260099 | B100: 45997 | C100: 3011 | D100: Common Area | E100: Medium | F100: Awaiting Vendor | G100: Coral Services | H100: Lobby HVAC warm | I100: 46013
...

Sheet Violations
A1: Violation ID | B1: Notice Date | C1: Unit | D1: Type | E1: Status | F1: Cure Deadline | G1: Fine | H1: Hearing Required | I1: Notes
A2: VIOL-20260001 | B2: 46075 | C2: 2305 | D2: Short-term rental | E2: Open | F2: 46089 | G2: 250 | H2: N | I2: Resident contacted by phone
A3: VIOL-20260002 | B3: 45978 | C3: 2707 | D3: Short-term rental | E3: Open | F3: 45985 | G3: 50 | H3: N | I3: Board review required
A4: VIOL-20260003 | B4: 45904 | C4: 2409 | D4: Balcony | E4: Open | F4: 45911 | G4: 250 | H4: N | I4: Board review required
A5: VIOL-20260004 | B5: 45981 | C5: 1901 | D5: Short-term rental | E5: Hearing Scheduled | F5: 45991 | G5: 25 | H5: Y | I5: Board review required
A6: VIOL-20260005 | B6: 45937 | C6: 2009 | D6: Parking | E6: Fine Assessed | F6: 45951 | G6: 100 | H6: Y | I6: Resident contacted by phone
A7: VIOL-20260006 | B7: 45918 | C7: 116 | D7: Balcony | E7: Fine Assessed | F7: 45928 | G7: 50 | H7: Y | I7: Second notice sent
A8: VIOL-20260007 | B8: 46000 | C8: 3407 | D8: Parking | E8: Cured | F8: 46021 | G8: 0 | H8: N | I8: Board review required
A9: VIOL-20260008 | B9: 45920 | C9: 2812 | D9: Noise | E9: Cured | F9: 45941 | G9: 100 | H9: N | I9: Resident contacted by phone
A10: VIOL-20260009 | B10: 45942 | C10: 3905 | D10: Pet | E10: Cured | F10: 45963 | G10: 100 | H10: N | I10: Photo on file in portal
A11: VIOL-20260010 | B11: 45982 | C11: 215 | D11: Balcony | E11: Fine Assessed | F11: 45992 | G11: 25 | H11: Y | I11: Photo on file in portal
A12: VIOL-20260011 | B12: 45930 | C12: 2807 | D12: Short-term rental | E12: Open | F12: 45940 | G12: 0 | H12: N | I12: Photo on file in portal
A13: VIOL-20260012 | B13: 46053 | C13: 817 | D13: Balcony | E13: Hearing Scheduled | F13: 46067 | G13: 50 | H13: N
A14: VIOL-20260013 | B14: 45942 | C14: 3514 | D14: Pet | E14: Closed | F14: 45963 | G14: 0 | H14: N | I14: Courtesy warning
A15: VIOL-20260014 | B15: 46055 | C15: 3406 | D15: Short-term rental | E15: Hearing Scheduled | F15: 46069 | G15: 0 | H15: N | I15: Board review required
A16: VIOL-20260015 | B16: 45983 | C16: 2104 | D16: Pet | E16: Closed | F16: 45990 | G16: 50 | H16: N | I16: Board review required
A17: VIOL-20260016 | B17: 45959 | C17: 1809 | D17: Noise | E17: Fine Assessed | F17: 45969 | G17: 50 | H17: Y | I17: Resident contacted by phone
A18: VIOL-20260017 | B18: 46028 | C18: 4804 | D18: Parking | E18: Cured | F18: 46038 | G18: 25 | H18: N | I18: Photo on file in portal
A19: VIOL-20260018 | B19: 45920 | C19: 4316 | D19: Pet | E19: Closed | F19: 45941 | G19: 25 | H19: N | I19: Second notice sent
A20: VIOL-20260019 | B20: 46034 | C20: 909 | D20: Pet | E20: Cured | F20: 46041 | G20: 50 | H20: N | I20: Photo on file in portal
A21: VIOL-20260020 | B21: 46008 | C21: 4408 | D21: Noise | E21: Open | F21: 46018 | G21: 0 | H21: N | I21: Resident contacted by phone
A22: VIOL-20260021 | B22: 45987 | C22: 4201 | D22: Balcony | E22: Cured | F22: 45994 | G22: 25 | H22: N | I22: Board review required
A23: VIOL-20260022 | B23: 45946 | C23: 811 | D23: Parking | E23: Fine Assessed | F23: 45956 | G23: 25 | H23: Y | I23: Photo on file in portal
A24: VIOL-20260023 | B24: 45928 | C24: 202 | D24: Architectural | E24: Open | F24: 45949 | G24: 0 | H24: N
A25: VIOL-20260024 | B25: 45988 | C25: 2512 | D25: Parking | E25: Open | F25: 45998 | G25: 0 | H25: N | I25: Second notice sent
A26: VIOL-20260025 | B26: 46004 | C26: 2906 | D26: Architectural | E26: Cured | F26: 46018 | G26: 250 | H26: N | I26: Courtesy warning
A27: VIOL-20260026 | B27: 46074 | C27: 409 | D27: Parking | E27: Cured | F27: 46084 | G27: 0 | H27: N
A28: VIOL-20260027 | B28: 46008 | C28: 4404 | D28: Balcony | E28: Open | F28: 46029 | G28: 0 | H28: N | I28: Board review required
A29: VIOL-20260028 | B29: 45937 | C29: 4815 | D29: Noise | E29: Open | F29: 45944 | G29: 0 | H29: N | I29: Courtesy warning
A30: VIOL-20260029 | B30: 45932 | C30: 3911 | D30: Noise | E30: Closed | F30: 45939 | G30: 0 | H30: N | I30: Resident contacted by phone
A31: VIOL-20260030 | B31: 45980 | C31: 102 | D31: Pet | E31: Closed | F31: 45987 | G31: 250 | H31: N | I31: Photo on file in portal
A32: VIOL-20260031 | B32: 45995 | C32: 1204 | D32: Balcony | E32: Hearing Scheduled | F32: 46002 | G32: 250 | H32: Y | I32: Board review required
A33: VIOL-20260032 | B33: 46062 | C33: 5008 | D33: Pet | E33: Open | F33: 46069 | G33: 50 | H33: N | I33: Photo on file in portal
A34: VIOL-20260033 | B34: 45965 | C34: 3613 | D34: Balcony | E34: Open | F34: 45986 | G34: 25 | H34: N
A35: VIOL-20260034 | B35: 45908 | C35: 604 | D35: Short-term rental | E35: Fine Assessed | F35: 45922 | G35: 100 | H35: N
A36: VIOL-20260035 | B36: 46000 | C36: 1412 | D36: Short-term rental | E36: Open | F36: 46021 | G36: 50 | H36: N | I36: Resident contacted by phone
A37: VIOL-20260036 | B37: 45933 | C37: 3509 | D37: Parking | E37: Closed | F37: 45947 | G37: 0 | H37: N | I37: Resident contacted by phone
A38: VIOL-20260037 | B38: 46010 | C38: 1714 | D38: Architectural | E38: Hearing Scheduled | F38: 46031 | G38: 250 | H38: Y | I38: Resident contacted by phone
A39: VIOL-20260038 | B39: 45944 | C39: 909 | D39: Architectural | E39: Open | F39: 45958 | G39: 100 | H39: N | I39: Photo on file in portal
A40: VIOL-20260039 | B40: 46021 | C40: 4708 | D40: Noise | E40: Open | F40: 46035 | G40: 25 | H40: N | I40: Photo on file in portal
A41: VIOL-20260040 | B41: 46036 | C41: 2204 | D41: Noise | E41: Fine Assessed | F41: 46057 | G41: 0 | H41: N | I41: Photo on file in portal
A42: VIOL-20260041 | B42: 45956 | C42: 1815 | D42: Parking | E42: Closed | F42: 45970 | G42: 50 | H42: N | I42: Courtesy warning
A43: VIOL-20260042 | B43: 45941 | C43: 4701 | D43: Short-term rental | E43: Open | F43: 45951 | G43: 50 | H43: N | I43: Resident contacted by phone
A44: VIOL-20260043 | B44: 46060 | C44: 2508 | D44: Short-term rental | E44: Closed | F44: 46081 | G44: 0 | H44: N
A45: VIOL-20260044 | B45: 45966 | C45: 2717 | D45: Parking | E45: Cured | F45: 45980 | G45: 25 | H45: N | I45: Resident contacted by phone
A46: VIOL-20260045 | B46: 45947 | C46: 1213 | D46: Pet | E46: Closed | F46: 45961 | G46: 0 | H46: N | I46: Board review required
A47: VIOL-20260046 | B47: 45914 | C47: 1817 | D47: Balcony | E47: Open | F47: 45921 | G47: 25 | H47: N | I47: Courtesy warning
A48: VIOL-20260047 | B48: 46062 | C48: 2715 | D48: Short-term rental | E48: Closed | F48: 46069 | G48: 50 | H48: N | I48: Courtesy warning
A49: VIOL-20260048 | B49: 45961 | C49: 3806 | D49: Balcony | E49: Open | F49: 45982 | G49: 0 | H49: N | I49: Second notice sent
A50: VIOL-20260049 | B50: 45931 | C50: 1201 | D50: Noise | E50: Open | F50: 45938 | G50: 100 | H50: N | I50: Courtesy warning
A51: VIOL-20260050 | B51: 45992 | C51: 708 | D51: Parking | E51: Fine Assessed | F51: 46006 | G51: 250 | H51: Y | I51: Resident contacted by phone
A52: VIOL-20260051 | B52: 46049 | C52: 1502 | D52: Parking | E52: Open | F52: 46056 | G52: 50 | H52: N | I52: Resident contacted by phone
A53: VIOL-20260052 | B53: 45976 | C53: 613 | D53: Pet | E53: Fine Assessed | F53: 45986 | G53: 25 | H53: N
A54: VIOL-20260053 | B54: 45962 | C54: 4202 | D54: Balcony | E54: Fine Assessed | F54: 45972 | G54: 0 | H54: Y | I54: Board review required
A55: VIOL-20260054 | B55: 45917 | C55: 2306 | D55: Short-term rental | E55: Open | F55: 45931 | G55: 250 | H55: N | I55: Photo on file in portal
A56: VIOL-20260055 | B56: 45901 | C56: 1112 | D56: Architectural | E56: Closed | F56: 45911 | G56: 0 | H56: N | I56: Board review required
A57: VIOL-20260056 | B57: 45995 | C57: 4805 | D57: Noise | E57: Fine Assessed | F57: 46002 | G57: 0 | H57: Y | I57: Board review required
A58: VIOL-20260057 | B58: 45896 | C58: 401 | D58: Parking | E58: Open | F58: 45906 | G58: 250 | H58: N | I58: Second notice sent
A59: VIOL-20260058 | B59: 45987 | C59: 4902 | D59: Pet | E59: Fine Assessed | F59: 46001 | G59: 50 | H59: Y | I59: Resident contacted by phone
A60: VIOL-20260059 | B60: 45989 | C60: 216 | D60: Balcony | E60: Open | F60: 46010 | G60: 0 | H60: N | I60: Board review required
A61: VIOL-20260060 | B61: 45895 | C61: 1209 | D61: Short-term rental | E61: Cured | F61: 45902 | G61: 25 | H61: N
A62: VIOL-20260061 | B62: 45924 | C62: 4111 | D62: Balcony | E62: Open | F62: 45934 | G62: 250 | H62: N | I62: Photo on file in portal
A63: VIOL-20260062 | B63: 46063 | C63: 110 | D63: Architectural | E63: Open | F63: 46073 | G63: 25 | H63: N
A64: VIOL-20260063 | B64: 46072 | C64: 1305 | D64: Noise | E64: Fine Assessed | F64: 46079 | G64: 25 | H64: Y | I64: Photo on file in portal
A65: VIOL-20260064 | B65: 46021 | C65: 2614 | D65: Parking | E65: Fine Assessed | F65: 46035 | G65: 0 | H65: Y | I65: Courtesy warning
A66: VIOL-20260065 | B66: 45915 | C66: 3717 | D66: Short-term rental | E66: Closed | F66: 45929 | G66: 100 | H66: N | I66: Resident contacted by phone
A67: VIOL-20260066 | B67: 46031 | C67: 3315 | D67: Balcony | E67: Hearing Scheduled | F67: 46041 | G67: 25 | H67: N | I67: Courtesy warning
A68: VIOL-20260067 | B68: 46038 | C68: 313 | D68: Balcony | E68: Open | F68: 46045 | G68: 50 | H68: N | I68: Board review required
A69: VIOL-20260068 | B69: 45930 | C69: 3514 | D69: Parking | E69: Open | F69: 45951 | G69: 100 | H69: N | I69: Photo on file in portal
A70: VIOL-20260069 | B70: 46057 | C70: 3316 | D70: Balcony | E70: Cured | F70: 46071 | G70: 0 | H70: N
A71: VIOL-20260070 | B71: 46014 | C71: 2915 | D71: Pet | E71: Fine Assessed | F71: 46024 | G71: 250 | H71: N | I71: Second notice sent
A72: VIOL-20260071 | B72: 45906 | C72: 1212 | D72: Pet | E72: Open | F72: 45920 | G72: 0 | H72: N | I72: Photo on file in portal
A73: VIOL-20260072 | B73: 46075 | C73: 2412 | D73: Balcony | E73: Cured | F73: 46085 | G73: 25 | H73: N | I73: Courtesy warning
A74: VIOL-20260073 | B74: 46073 | C74: 1403 | D74: Parking | E74: Open | F74: 46080 | G74: 0 | H74: N | I74: Board review required
A75: VIOL-20260074 | B75: 46021 | C75: 2315 | D75: Balcony | E75: Open | F75: 46042 | G75: 0 | H75: N | I75: Courtesy warning
A76: VIOL-20260075 | B76: 46048 | C76: 2812 | D76: Pet | E76: Open | F76: 46055 | G76: 250 | H76: N | I76: Second notice sent
A77: VIOL-20260076 | B77: 45906 | C77: 3509 | D77: Noise | E77: Open | F77: 45916 | G77: 25 | H77: N | I77: Courtesy warning
A78: VIOL-20260077 | B78: 46051 | C78: 504 | D78: Parking | E78: Hearing Scheduled | F78: 46058 | G78: 250 | H78: N | I78: Board review required
A79: VIOL-20260078 | B79: 45902 | C79: 314 | D79: Balcony | E79: Open | F79: 45923 | G79: 100 | H79: N | I79: Courtesy warning
A80: VIOL-20260079 | B80: 46013 | C80: 115 | D80: Parking | E80: Closed | F80: 46020 | G80: 50 | H80: N | I80: Board review required
A81: VIOL-20260080 | B81: 45962 | C81: 1405 | D81: Noise | E81: Fine Assessed | F81: 45969 | G81: 25 | H81: N | I81: Courtesy warning
A82: VIOL-20260081 | B82: 45959 | C82: 2103 | D82: Noise | E82: Closed | F82: 45980 | G82: 25 | H82: N | I82: Resident contacted by phone
A83: VIOL-20260082 | B83: 46028 | C83: 605 | D83: Parking | E83: Hearing Scheduled | F83: 46049 | G83: 25 | H83: Y | I83: Photo on file in portal
A84: VIOL-20260083 | B84: 46016 | C84: 1509 | D84: Balcony | E84: Closed | F84: 46026 | G84: 0 | H84: N
A85: VIOL-20260084 | B85: 46039 | C85: 2810 | D85: Balcony | E85: Cured | F85: 46046 | G85: 25 | H85: N | I85: Board review required
A86: VIOL-20260085 | B86: 45957 | C86: 209 | D86: Noise | E86: Open | F86: 45978 | G86: 0 | H86: N | I86: Photo on file in portal
A87: VIOL-20260086 | B87: 45987 | C87: 1013 | D87: Parking | E87: Hearing Scheduled | F87: 45994 | G87: 0 | H87: Y
A88: VIOL-20260087 | B88: 46032 | C88: 617 | D88: Pet | E88: Fine Assessed | F88: 46042 | G88: 0 | H88: Y | I88: Resident contacted by phone
A89: VIOL-20260088 | B89: 46044 | C89: 3208 | D89: Pet | E89: Cured | F89: 46051 | G89: 250 | H89: N | I89: Courtesy warning
A90: VIOL-20260089 | B90: 45931 | C90: 612 | D90: Balcony | E90: Hearing Scheduled | F90: 45952 | G90: 0 | H90: Y | I90: Courtesy warning
A91: VIOL-20260090 | B91: 45935 | C91: 3403 | D91: Parking | E91: Fine Assessed | F91: 45949 | G91: 100 | H91: N
A92: VIOL-20260091 | B92: 45955 | C92: 1102 | D92: Noise | E92: Open | F92: 45962 | G92: 250 | H92: N | I92: Photo on file in portal
A93: VIOL-20260092 | B93: 45989 | C93: 1505 | D93: Balcony | E93: Hearing Scheduled | F93: 45999 | G93: 0 | H93: Y | I93: Board review required
A94: VIOL-20260093 | B94: 45920 | C94: 1006 | D94: Pet | E94: Fine Assessed | F94: 45930 | G94: 100 | H94: Y | I94: Courtesy warning
A95: VIOL-20260094 | B95: 46062 | C95: 4011 | D95: Parking | E95: Cured | F95: 46072 | G95: 250 | H95: N | I95: Board review required
A96: VIOL-20260095 | B96: 46034 | C96: 102 | D96: Parking | E96: Fine Assessed | F96: 46048 | G96: 100 | H96: Y | I96: Second notice sent
A97: VIOL-20260096 | B97: 46041 | C97: 4016 | D97: Architectural | E97: Open | F97: 46048 | G97: 25 | H97: N | I97: Courtesy warning
A98: VIOL-20260097 | B98: 45951 | C98: 1714 | D98: Pet | E98: Hearing Scheduled | F98: 45958 | G98: 0 | H98: Y | I98: Courtesy warning
A99: VIOL-20260098 | B99: 45928 | C99: 3705 | D99: Noise | E99: Hearing Scheduled | F99: 45938 | G99: 250 | H99: Y | I99: Photo on file in portal
A100: VIOL-20260099 | B100: 46043 | C100: 303 | D100: Pet | E100: Closed | F100: 46057 | G100: 250 | H100: N
...

Sheet Notices
A1: Notice ID | B1: Sent Date | C1: Category | D1: Title | E1: Delivery | F1: Summary
A2: NTC-2026001 | B2: 46012 | C2: Safety | D2: Fire Alarm Testing — Tower A | E2: SMS | F2: Work will occur overnight to minimize disruption. Expect brief elevator downtime per bank.
A3: NTC-2026002 | B3: 45987 | C3: Amenities | D3: Valet Service Hours Update | E3: Portal | F3: New RFID readers will be installed. Existing fobs will continue to work after migration.
A4: NTC-2026003 | B4: 45963 | C4: Finance | D4: Annual Budget Meeting Notice | E4: SMS | F4: Water will be off 9am–1pm. Please plan accordingly and report any leaks after restore.
A5: NTC-2026004 | B5: 46016 | C5: Safety | D5: Water Shutoff Notice (Floors 12–18) | E5: SMS | F5: Special assessment remains in effect. Online portal supports one-time or scheduled payments.
A6: NTC-2026005 | B6: 46020 | C6: Governance | D6: Board Meeting Agenda & Dial-in Details | E6: Email+SMS | F6: Agenda includes vendor contract renewals, reserve study update, and rule enforcement.
A7: NTC-2026006 | B7: 46051 | C7: Safety | D7: Fire Alarm Testing — Tower A | E7: Portal | F7: Work will occur overnight to minimize disruption. Expect brief elevator downtime per bank.
A8: NTC-2026007 | B8: 46061 | C8: Hurricane Prep | D8: Hurricane Season Preparation Checklist | E8: Email | F8: Work will occur overnight to minimize disruption. Expect brief elevator downtime per bank.
A9: NTC-2026008 | B9: 45957 | C9: Operations | D9: Garage Gate Access System Upgrade | E9: SMS | F9: Water will be off 9am–1pm. Please plan accordingly and report any leaks after restore.
A10: NTC-2026009 | B10: 45956 | C10: Amenities | D10: Valet Service Hours Update | E10: Email | F10: Work will occur overnight to minimize disruption. Expect brief elevator downtime per bank.
A11: NTC-2026010 | B11: 45957 | C11: Operations | D11: Garage Gate Access System Upgrade | E11: Email+SMS | F11: Updated hours effective next week. After-hours service available by request.
A12: NTC-2026011 | B12: 45991 | C12: Operations | D12: Elevator Preventive Maintenance Schedule | E12: Email | F12: Work will occur overnight to minimize disruption. Expect brief elevator downtime per bank.
A13: NTC-2026012 | B13: 45958 | C13: Finance | D13: Annual Budget Meeting Notice | E13: Portal | F13: Budget packet available in the portal. Owners may attend in person or via conference line.
... A21: NTC-2026020 | B21: 45985 | C21: Finance | D21: Annual Budget Meeting Notice | E21: Portal | F21: Budget packet available in the portal. Owners may attend in person or via conference line.

Sheet SMS_Test_Set
A1: Scenario ID | B1: Channel | C1: From | D1: Unit | E1: Message | F1: Expected Data | G1: Notes
A2: SCN-001 | B2: SMS | C2: (305) 555-6001 | D2: 3806 | E2: What is my current balance? | F2: Current Balance | G2: Balance inquiry
A3: SCN-002 | B3: SMS | C3: (305) 555-6002 | D3: 3415 | E3: What is my current balance? | F3: Current Balance | G3: Balance inquiry
A4: SCN-003 | B4: Voice | C4: (305) 555-6003 | D4: 4105 | E4: Am I enrolled in autopay? | F4: Autopay | G4: Autopay
A5: SCN-004 | B5: SMS | C5: (305) 555-6004 | D5: 3304 | E5: Is my work order still open? | F5: Work Orders | G5: Work order status
A6: SCN-005 | B6: SMS | C6: (305) 555-6005 | D6: 1416 | E6: When does my tenant lease expire? | F6: Lease Expiration | G6: Lease
A7: SCN-006 | B7: Voice | C7: (305) 555-6006 | D7: 3513 | E7: Do I have a special assessment? | F7: Special Assessment Active | G7: Special assessment
A8: SCN-007 | B8: SMS | C8: (305) 555-6007 | D8: 2612 | E8: Is my work order still open? | F8: Work Orders | G8: Work order status
A9: SCN-008 | B9: SMS | C9: (305) 555-6008 | D9: 1804 | E9: Do I have a boat slip assigned? | F9: Boat Slip | G9: Boat slip
A10: SCN-009 | B10: SMS | C10: (305) 555-6009 | D10: 508 | E10: Do I have a boat slip assigned? | F10: Boat Slip | G10: Boat slip
A11: SCN-010 | B11: SMS | C11: (305) 555-6010 | D11: 3217 | E11: When does my tenant lease expire? | F11: Lease Expiration | G11: Lease
A12: SCN-011 | B12: SMS | C12: (305) 555-6011 | D12: 3705 | E12: Is my work order still open? | F12: Work Orders | G12: Work order status
... A61: SCN-060 | B61: SMS | C61: (305) 555-6060 | D61: 3217 | E61: When does my tenant lease expire? | F61: Lease Expiration | G61: Lease
